{"type":"PR","pr":{"number":3,"head":"f8ec94234ff2a2e083fe4748eda6826886069acb"},"user":"ECN Technology","status":"pending_publish","branch":"cms/mycloudpbx/device-configuration","collection":"mycloudpbx","commitMessage":"Update myCloudPBX articles “device-configuration”","title":"Device Configuration","description":"No Description!","objects":{"entry":{"path":"guides/mycloudpbx/device-configuration.md","sha":"bcf08a0ecd2dd23ce0732c241b08d1a895d362fc"},"files":[]},"timeStamp":"2020-02-22T07:06:41.495Z","version":"1"}